{
  "resourceType": "ClinicalUseDefinition",
  "id": "db00273-partial-epilepsy",
  "type": "indication",
  "subject": [
    {
      "reference": "MedicationKnowledge/db00273"
    }
  ],
  "indication": {
    "diseaseSymptomProcedure": {
      "concept": {
        "text": "partial epilepsy"
      }
    }
  },
  "extension": [
    {
      "url": "https://satxgnn.yao.care/fhir/StructureDefinition/evidence-level",
      "valueCode": "L5"
    },
    {
      "url": "https://satxgnn.yao.care/fhir/StructureDefinition/txgnn-score",
      "valueDecimal": 0.5
    }
  ]
}