{
  "resourceType": "ClinicalUseDefinition",
  "id": "db09310-factor-xiii,-a-subunit,-deficiency",
  "type": "indication",
  "subject": [
    {
      "reference": "MedicationKnowledge/db09310"
    }
  ],
  "indication": {
    "diseaseSymptomProcedure": {
      "concept": {
        "text": "factor XIII, A subunit, deficiency"
      }
    }
  },
  "extension": [
    {
      "url": "https://satxgnn.yao.care/fhir/StructureDefinition/evidence-level",
      "valueCode": "L5"
    },
    {
      "url": "https://satxgnn.yao.care/fhir/StructureDefinition/txgnn-score",
      "valueDecimal": 0.5
    }
  ]
}