{
  "resourceType": "MedicationKnowledge",
  "id": "db00277",
  "status": "active",
  "code": {
    "coding": [
      {
        "system": "https://satxgnn.yao.care/drugs",
        "code": "db00277",
        "display": "DB00277"
      }
    ]
  },
  "intendedJurisdiction": [
    {
      "coding": [
        {
          "system": "urn:iso:std:iso:3166",
          "code": "SA",
          "display": "Saudi Arabia"
        }
      ]
    }
  ],
  "extension": [
    {
      "url": "https://satxgnn.yao.care/fhir/StructureDefinition/evidence-level",
      "valueCode": "L5"
    }
  ]
}